rmc_discord.libs/libgomp-a34b3233.so.1.0.0
rmc_discord-0.0.4.dist-info/LICENSE
rmc_discord-0.0.4.dist-info/entry_points.txt
rmc_discord-0.0.4.dist-info/METADATA
rmc_discord-0.0.4.dist-info/top_level.txt
rmc_discord-0.0.4.dist-info/WHEEL
rmc_discord-0.0.4.dist-info/RECORD
disorder/application.py
disorder/version.py
disorder/__init__.py
disorder/correlation/__init__.py
disorder/correlation/functions.cpython-38-x86_64-linux-gnu.so
disorder/diffuse/space.py
disorder/diffuse/scattering.py
disorder/diffuse/powder.cpython-38-x86_64-linux-gnu.so
disorder/diffuse/filters.pxd
disorder/diffuse/powder.pyx
disorder/diffuse/simulation.pyx
disorder/diffuse/filters.cpython-38-x86_64-linux-gnu.so
disorder/diffuse/refinement.cpython-38-x86_64-linux-gnu.so
disorder/diffuse/monocrystal.pyx
disorder/diffuse/simulation.pxd
disorder/diffuse/experimental.py
disorder/diffuse/interaction.py
disorder/diffuse/occupational.py
disorder/diffuse/refinement.pxd
disorder/diffuse/filters.pyx
disorder/diffuse/__init__.py
disorder/diffuse/__init__.pxd
disorder/diffuse/monocrystal.cpython-38-x86_64-linux-gnu.so
disorder/diffuse/refinement.pyx
disorder/diffuse/magnetic.py
disorder/diffuse/nonmagnetic.py
disorder/diffuse/simulation.cpython-38-x86_64-linux-gnu.so
disorder/diffuse/displacive.py
disorder/material/e.csv
disorder/material/groups.csv
disorder/material/crystal.py
disorder/material/structure.py
disorder/material/radii.csv
disorder/material/tables.py
disorder/material/symmetry.py
disorder/material/__init__.py
disorder/material/z.csv
disorder/material/__init__.pxd
disorder/material/j0.csv
disorder/material/j2.csv
disorder/material/colors.csv
disorder/material/b.csv
disorder/material/x.csv
disorder/graphical/canvas.py
disorder/graphical/plots.py
disorder/graphical/visualization.py
disorder/graphical/model.py
disorder/graphical/mainwindow.ui
disorder/graphical/utilities.py
disorder/graphical/__init__.py
disorder/graphical/view.py
disorder/graphical/presenter.py
disorder/graphical/logo.png
disorder/graphical/dialog.ui
disorder/tests/__init__.py
disorder/tests/data/Ba3Co2O6(CO3)0.6.cif
disorder/tests/data/H2O.cif
disorder/tests/data/CuMnO2.mcif
