Metadata-Version: 2.1
Name: rmc-discord
Version: 0.0.4
Summary: Reverse Monte Carlo refinement of diffuse scattering and correlated disorder from single crystals
Home-page: https://github.com/zjmorgan/rmc-discord
Author: Zachary Morgan
Author-email: morganzj@ornl.gov
Classifier: Programming Language :: Python :: 3
Classifier: License :: OSI Approved :: GNU General Public License (GPL)
Classifier: Operating System :: OS Independent
Requires-Python: >=3.6
License-File: LICENSE
